setup.cfg
setup.py
isphere/__init__.py
isphere/cli.py
isphere/connection.py
isphere/input.py
isphere/interactive_wrapper.py
isphere.egg-info/PKG-INFO
isphere.egg-info/SOURCES.txt
isphere.egg-info/dependency_links.txt
isphere.egg-info/entry_points.txt
isphere.egg-info/requires.txt
isphere.egg-info/top_level.txt
isphere.egg-info/zip-safe
isphere/command/__init__.py
isphere/command/core_command.py
isphere/command/dvs_command.py
isphere/command/esx_command.py
isphere/command/virtual_machine_command.py
scripts/isphere
thirdparty/__init__.py
thirdparty/tasks.py