Metadata-Version: 1.1
Name: isphere
Version: 0.0.1
Summary: interactive shell for vsphere
Home-page: https://github.com/mriehl/isphere
Author: Maximilien Riehl
Author-email: max@riehl.io
License: WTFPL
Platform: UNKNOWN
Classifier: Development Status :: 4 - Beta
Classifier: Environment :: Console
Classifier: Intended Audience :: Developers
Classifier: Intended Audience :: System Administrators
Classifier: Programming Language :: Python
Classifier: Topic :: System :: Systems Administration
